df_chat/__init__.py
df_chat/admin.py
df_chat/apps.py
df_chat/constants.py
df_chat/defaults.py
df_chat/models.py
df_chat/paginators.py
df_chat/permissions.py
df_chat/settings.py
df_chat/signals.py
df_chat/utils.py
df_chat/asgi/__init__.py
df_chat/asgi/consumers.py
df_chat/asgi/routing.py
df_chat/drf/__init__.py
df_chat/drf/serializers.py
df_chat/drf/urls.py
df_chat/drf/viewsets.py
df_chat/migrations/0001_initial.py
df_chat/migrations/__init__.py
django_df_chat-0.1.7.dist-info/LICENSE
django_df_chat-0.1.7.dist-info/METADATA
django_df_chat-0.1.7.dist-info/WHEEL
django_df_chat-0.1.7.dist-info/top_level.txt
django_df_chat-0.1.7.dist-info/RECORD
